{"title": "小米竖版折叠屏手机渲染图曝光：这外观很难评小米折叠屏", "news_website": "新浪科技", "author": "", "Managing Editor": "：建嘉", "details": {"creation_time": "2023年06月16日 08:06", "keywords": ["小米", "折叠屏"]}, "content": ["据爆料，小米和荣耀都相继加入了竖向折叠屏手机阵营。近段时间网上关于荣耀竖向折叠屏手机的爆料越来越多，消息显示这款手机会在今年亮相。", "手机正面采用单挖孔屏设计，四边框较窄，视觉观感不错。整体来看，小米竖版折叠屏手机辨识度是有了，但美观度似乎还差一点。", "幸运的是，这只是博主自己做的渲染图，估计小米官方应该能将手机打磨地更好看。", "当下小折叠屏手机越来越受到消费者追捧。不久前，moto带来了新款小折叠屏手机moto razr 40系列，不仅在多个领域刷新了小折叠屏手机产品的历史记录，而且还将小折叠屏手机的价格拉到了新低，起售价低至3999元，带给了其他手机厂商很多压力。", "至于发布时间，目前网上没有太多关于小米小折叠屏手机发布时间的爆料，猜测新机最高可能会在今年发布，晚一点的话或许要明年。"], "urls": {"webpage": "https://finance.sina.com.cn/tech/mobile/n/n/2023-06-16/doc-imyxkxpy5650192.shtml", "image_url": ["https://n.sinaimg.cn/spider20230615/620/w600h820/20230615/1dc7-da14756c0ffddf7941d6233f0b214ce9.jpg", "https://n.sinaimg.cn/spider20230615/400/w600h600/20230615/32a2-58a0f1615c3c3d50eed2b479f42a1219.jpg"]}}