{"title": "GitHub计划在财年内裁员10% 还计划转向远程办公githubtechcrunch办公室", "news_website": "新浪科技", "author": "", "Managing Editor": "", "details": {"creation_time": "2023年02月10日 09:25", "keywords": ["github", "techcrunch", "办公室"]}, "content": ["品玩2月10日讯，据 TechCrunch 报道，GitHub 今天宣布，将会在本财年结束前裁员10%。目前 GitHub约有3000名员工。", "除了裁员之外，GitHub 还将继续冻结招聘工作，并进行一些内部调整以保护其业务的健康。另外， GitHub还计划在房租到期后关闭其所有办公室，转向远程办公。"], "urls": {"webpage": "https://finance.sina.com.cn/tech/roll/2023-02-10/doc-imyfekfw6229072.shtml", "image_url": ["https://n.sinaimg.cn/spider20230210/360/w750h410/20230210/755b-318c053da15fa7c211567279587e41bf.jpg"]}}