{"title": "史诗级升级！曝iPhone 15 Pro支持雷电3iPhoneUSB雷电3", "news_website": "科技频道", "author": "", "Managing Editor": "：振亭", "details": {"creation_time": "2023年04月28日07:34", "keywords": []}, "content": ["利用雷电3的优势，苹果为iPhone 15 Pro和15 Pro Max开发了一项新功能，在手机进行4K录制时，画面可以实时同步到外接显示器上。", "据悉，雷电3拥有传输速度快、支持双向传输等优势，其带宽高达40GB/s，是USB 3.0(5GB/s)的8倍、USB 3.1 (10GB/s）的4倍，一个10G左右的文件仅需2.5秒就能传输完成。", "由于它的高带宽，雷电3在拓展性方面也远比USB 3.0丰富不少，可以外接4K显示器、固态硬盘等等。", "值得注意的是，在充电方面，雷电3最高支持100W的PD快充。不过按照苹果的策略，iPhone 15 Pro系列应该不会支持这么高的快充规格，大概率还是“原地踏步”。", "【本文结束】如需转载请务必注明出处：快科技"], "urls": {"webpage": "https://finance.sina.com.cn/tech/mobile/n/n/2023-04-28/doc-imyrwtzz2866863.shtml", "image_url": ["https://n.sinaimg.cn/spider20230428/137/w600h337/20230428/b107-2f1e8c54b55d092790ac33b32019d267.jpg", "https://n.sinaimg.cn/8ee96216/20150312/weixin_apple.jpg"]}}