{"title": "400亿交易告吹 Intel雄心不变：2030年前成第二大半导体代工厂台积电代工厂半导体", "news_website": "新浪科技", "author": "", "Managing Editor": "：宪瑞", "details": {"creation_time": "2023年08月17日 13:18", "keywords": ["台积电", "代工厂", "半导体", "三星", "代工市场"]}, "content": ["快科技8月17日消息，由于没有获得监管部门的批准，Intel日前宣布放弃收购Tower高塔半导体的交易，价值400亿的收购案就此终结，Intel赔付了25.8亿元的违约金。", "按照Intel的目标，7年后全球半导体代工市场会是一次大洗牌，他们几乎是从零做到世界第二，仅次于台积电，毕竟后者在这方面的实力太强，Intel代工超越台积电没什么可能。", "当然，如果把三星的目标加进来就更有意思了，因为三星的计划是2030年成为半导体市场第一，代工市场也要超越台积电。", "这三家也是目前仅有的能发展5nm及以下先进工艺的半导体工厂，其中Intel做到第二的关键就是明年量产的Intel 3及Intel 18A工艺，相当于友商的3nm、1.8nm，按期量产的话Intel才有可能跟其他两家一较高下。", "【本文结束】如需转载请务必注明出处：快科技"], "urls": {"webpage": "https://finance.sina.com.cn/tech/discovery/2023-08-17/doc-imzhnsmx6418365.shtml", "image_url": ["https://n.sinaimg.cn/spider20230817/199/w600h399/20230817/6f6b-a86876cf42210a3c56bfdf6cf73959bd.jpg"]}}