{"title": "1499 元，联想小新 365 智能投影仪今晚开售：450CVIA 流明、开机无广告投影仪联想小新IT之家", "news_website": "新浪科技", "author": "", "Managing Editor": "", "details": {"creation_time": "2023年08月09日 22:19", "keywords": ["投影仪", "联想小新", "IT之家"]}, "content": ["IT之家 8 月 9 日消息，联想官方今日宣布：小新 365 智能投影仪 8 月 10 日 0 点正式开售，首发价 1499 元。", "联想小新 365 投影仪采用无损光学偏轴设计，内置小巧云台，支持 5-8° 任意调节，无需外接支架；拥有 450CVIA 流明（1500ANSI）亮度、1080P 分辨率，支持 HDR10 高动态解码技术；采用 Hi-lmprexVI Al 画质引擎，自动实现画面精准控光、智能场景识别。", "联想小新 365 投影仪采用高精度 CMOS 摄像头模组，配合多重智能算法及全新硬件梯形校正芯片，开机即可对画面进行自动对焦和梯形校正；拥有对称式 2*5W 全频扬声器，400ml 超大音腔；搭载 Hi-V560 芯片，存储规格 2GB+16GB，支持 2.4G+5.8G 频道；采用定制第 4 代全密闭式光机，IP5X 防尘，复合式散热运行噪音低至 28dB。", "IT之家附参数规格：", "广告声明：文内含有的对外跳转链接（包括不限于超链接、二维码、口令等形式），用于传递更多信息，节省甄选时间，结果仅供参考，IT之家所有文章均包含本声明。"], "urls": {"webpage": "https://finance.sina.com.cn/tech/digi/2023-08-09/doc-imzfrnvr7436284.shtml", "image_url": ["https://n.sinaimg.cn/spider20230809/271/w1080h3991/20230809/f153-03ba35591fff934a5ff442c83658f751.jpg", "https://n.sinaimg.cn/spider20230809/161/w925h6436/20230809/e8b3-a6a893b32c6b6a5cafd1e86bbe2765c2.png", "https://n.sinaimg.cn/spider20230809/418/w929h5089/20230809/59f2-152c8b49a69acd973e7f5960d9ff2c5d.png", "https://n.sinaimg.cn/spider20230809/632/w864h1368/20230809/7b95-d385972ba3249bdef3043df4c59a8955.png"]}}