{"title": "安卓机皇胜！三星S23 Ultra比iPhone 14 Pro Max更抗摔三星iPhone抗摔", "news_website": "新浪科技", "author": "", "Managing Editor": "", "details": {"creation_time": "2023年03月10日 07:15", "keywords": ["三星", "iPhone", "抗摔", "跌落测试"]}, "content": ["", "【手机中国新闻】上个月，三星发布了备受瞩目的Galaxy S23 Ultra，这是该品牌最强的智能手机，机身边框使用了装甲铝材质，屏幕表面覆盖了康宁Victus2大猩猩玻璃。现如今厂商们越来越重视手机的抗摔能力，为产品配备更好的材质，其中iPhone14 Pro Max的机身就采用了超瓷晶材质。手机中国注意到，YouTuber PhoneBuff将三星S23 Ultra和iPhone 14 Pro Max一起进行了跌落测试，给大家介绍这两款手机之间的耐摔程度对比。", "PhoneBuff的跌落测试一共有四轮。", "在第一轮中，三星S23 Ultra和iPhone 14 Pro Max的机身背面向下进行自由跌落测试，这两部手机都被摔得仰面朝天，不过它们正面的屏幕均没有受到损伤。但是三星S23 Ultra在机身背面的右上角和左下角两个位置出现了裂纹，机身其他区域完好无损；而iPhone 14 Pro Max的机身背面则受损严重，玻璃材质机身出现了大面积的裂纹。", "在第二轮的边框掉落测试中，iPhone 14 Pro Max的不锈钢框架仅受到了轻微的刮擦，而S23 Ultra的铝制框架受损更严重。", "第三轮测试中，两部手机都正面朝下摔在水泥地上，其中三星S23 Ultra的两侧双曲屏受损严重，屏幕中间区域没有出现裂纹；而iPhone 14 Pro Max的屏幕中间区域受损比较严重，而且屏幕玻璃上都已经有残渣出现。", "在第四次也是最后一次测试中，三星S23 Ultra和iPhone 14 Pro Max正面朝下摔在金属表面上，而且摔得比前几次更高。iPhone 14 Pro Max遭受了严重的损坏，部分保护玻璃丢失。", "在四轮跌落测试中，三星S23 Ultra获得了38分，比iPhone 14 Pro Max高出两分，以微弱优势赢得了测试。", ""], "urls": {"webpage": "https://finance.sina.com.cn/tech/mobile/n/n/2023-03-10/doc-imykitkc2940672.shtml", "image_url": ["https://n.sinaimg.cn/spider20230310/75/w500h375/20230310/9077-f7fac6f9b7074e02e767fe11cb51d1e6.jpg", "https://n.sinaimg.cn/spider20230310/135/w600h335/20230310/81a0-e4cfbb140d16387a3c1b582101a58ea5.png"]}}