{"title": "Gurman：首款搭载 M3 Pro 芯片的苹果 Mac 有望年底推出，12 核 CPU + 18 核 GPUGPU苹果内存", "news_website": "新浪科技", "author": "", "Managing Editor": "", "details": {"creation_time": "2023年05月14日 19:55", "keywords": ["GPU", "苹果", "内存", "台积电"]}, "content": ["如果爆料为真，与目前的 M2 Pro 芯片相比，M3 Pro 芯片将多 2 个 CPU 内核和 2 个 GPU 内核，以及多 4GB 统一内存。", "此外，苹果 M3 系列芯片预计将采用 3nm 制造工艺，意味着每个内核的性能也会提高，整体性能提升不只是多 2 个内核，IT之家将持续关注后续消息。"], "urls": {"webpage": "https://finance.sina.com.cn/tech/mobile/n/n/2023-05-15/doc-imytuits1194266.shtml", "image_url": ["https://n.sinaimg.cn/spider20230514/508/w871h437/20230514/d87d-26d98494eafc11d9315e25e70896b174.png", "https://n.sinaimg.cn/spider20230514/136/w744h192/20230514/59d2-1ea50ea9b9edd17bd7229ff9f3d8912a.png"]}}