{"title": "索尼官网教育优惠已开启：可获专享优惠券，累计最高 2360 元索尼it之家索尼中国在线商城", "news_website": "新浪科技", "author": "", "Managing Editor": "", "details": {"creation_time": "2023年07月24日 13:14", "keywords": ["索尼", "it之家", "索尼中国在线商城"]}, "content": ["广告声明：文内含有的对外跳转链接（包括不限于超链接、二维码、口令等形式），用于传递更多信息，节省甄选时间，结果仅供参考，IT之家所有文章均包含本声明。"], "urls": {"webpage": "https://finance.sina.com.cn/tech/digi/2023-07-24/doc-imzcuitx5545596.shtml", "image_url": ["https://n.sinaimg.cn/spider20230724/640/w792h1448/20230724/a8bd-25f3c1dd8d4ddda34a42fd78b80d6f64.png"]}}