{"title": "诺辉健康回应医疗反腐：未进院产品的进院节奏的确会受到影响", "news_website": "新浪财经", "author": "", "Managing Editor": "：刘万里 SF014", "details": {"creation_time": "2023年08月21日 18:00", "keywords": []}, "content": ["新浪科技讯 8月21日下午消息，诺辉健康在2023年度中期业绩媒体沟通会上表示，常卫清的放量是在医院的体检科，是依据体检套餐来进院，是自然流量而非与医生挂钩，目前来看，医疗反腐对已进院产品影响不大。", "不过，对于没有进院的产品而言，进院节奏的确会受到影响。“但未进院产品在未来6至12个月对我们的收入不会有太大贡献，医疗反腐对癌症早筛短期有一定的有限的影响，不过从长期来看是利好的，我们的产品的进院流程会进一步加快。”（原祎鸣）"], "urls": {"webpage": "https://finance.sina.com.cn/tech/it/2023-08-21/doc-imzhycmv3747515.shtml", "image_url": []}}