{"title": "特斯拉进军数据中心市场，称将新建同类首个数据中心特斯拉推特it之家", "news_website": "新浪科技", "author": "", "Managing Editor": "", "details": {"creation_time": "2023年08月15日 09:48", "keywords": ["特斯拉", "推特", "it之家"]}, "content": ["IT之家 8 月 15 日消息，特斯拉宣布将建造“同类第一个（1st of its kind）”数据中心，该公司正为其招聘相关人员，并收购一些现有的数据中心。", "数据中心是一个庞大的市场，规模超过 2500 亿美元（IT之家备注：当前约 1.82 万亿元人民币）。许多世界上最大的公司，虽然以其他产品为人所知，但都涉足这个领域，比如亚马逊 AWS、微软 Azure、谷歌 GCP 和 Meta。现在，特斯拉也要进军数据中心业务。", "广告声明：文内含有的对外跳转链接（包括不限于超链接、二维码、口令等形式），用于传递更多信息，节省甄选时间，结果仅供参考，IT之家所有文章均包含本声明。"], "urls": {"webpage": "https://finance.sina.com.cn/tech/digi/2023-08-15/doc-imzhftsc8462474.shtml", "image_url": ["https://n.sinaimg.cn/spider20230815/284/w1238h646/20230815/2c94-2d229996d2c0225fcbce9e248e3bb472.jpg"]}}