{"title": "Win11即将迎来一波重磅更新：补丁10GB 以后省心了Win11微软补丁", "news_website": "新浪科技", "author": "", "Managing Editor": "：宪瑞", "details": {"creation_time": "2023年03月21日 06:47", "keywords": ["Win11", "微软", "补丁"]}, "content": ["微软去年9月发布了Win11 22H2，这是Win11发布以来的首个年度更新，今年的23H2还有点时间，不过下周3月28日会有一次重磅更新，这次将启用UUP更新，补丁容量高达10GB。", "微软解释补丁容量这么大只是因为一次性分发，此后Win11 22H2的所有更新就是UUP方式了，大小就会跟之前的情况一样。", "值得一提的是，2023年微软还会推出“Moment 3”更新，也就是之前说的Win11 23H2，预计下半年发布。", "除了对折叠屏设备的优化外，“Moment 3”还可能带来包括Windows搜索界面的更新，以及更多收件箱应用程序的更新，这能够让它们在UI设计上，进一步现代化。", "【本文结束】如需转载请务必注明出处：快科技"], "urls": {"webpage": "https://finance.sina.com.cn/tech/mobile/n/n/2023-03-21/doc-imymqrrf9888370.shtml", "image_url": ["https://n.sinaimg.cn/spider20230321/200/w600h400/20230321/4c53-c5cd89195024aefaf8153e5f73634046.jpg"]}}