{"title": "亚马逊云科技：将为100所中国高校免费提供云计算学习资源", "news_website": "新浪财经", "author": "", "Managing Editor": "：刘万里 SF014", "details": {"creation_time": "2023年08月17日 15:02", "keywords": []}, "content": ["新浪科技讯 8月17日下午消息，近日，亚马逊云科技宣布推出“百校行”计划，将携手合作伙伴免费为中国百所高校的学生提供云计算学习和实践的资源和平台，从课程资源、以赛促学和提升就业能力三个方面，帮助高校培养高素质的云计算人才。", "据介绍，目前亚马逊云科技已先后在深圳职业技术大学、大连东软信息学院、昆明冶金高等专科学校、郑州信息工程职业学院、广东职业技术学院、黑龙江职业学院、哈尔滨理工大学等学校开展了线下和线上活动，累计触达数千名学生学习云计算课程并参与 Amazon DeepRacer无人驾驶赛车比赛。", "亚马逊云科技承诺，到2025年将通过提供免费云计算技术培训，帮助包括中国在内的全球2900万人提高云计算技能。（文猛）"], "urls": {"webpage": "https://finance.sina.com.cn/tech/it/2023-08-17/doc-imzhnwuc8382424.shtml", "image_url": []}}