{"title": "多家高校停用微信支付，这些渠道正常使用西北大学周口师范学院", "news_website": "新浪科技", "author": "", "Managing Editor": "", "details": {"creation_time": "2023年06月29日 12:27", "keywords": ["西北大学", "周口师范学院"]}, "content": ["多家高校停用微信支付，据报道，西北大学、周口师范学院、郑州轻工业大学、郑州航空工业管理学院等高校均发布公告称，暂停或者关闭微信支付渠道。", "关于高校停用微信支付的原因，可能与微信支付收取手续费有关。西北大学发布的公告中提到，“因腾讯公司微信支付将于7月1日起对校园场景用户进行精细化管理，除收学费外，其它收费均会受到限制并收取0.6%的手续费。为维护师生利益，从6月30日起对校内一卡通用户暂停提供微信扫码支付服务。”", "有些高校受影响的场景较多，周口师范学院提到，停用微信支付的应用场景有：财务处收取的各类费用、校园一卡通充值、教材费缴费、教职工生活区网络交费、学生宿舍空调电费交费、商业用房电费交费、西苑1舍青年教师公寓电费交费。", "多份公告中提到，云闪付、支付宝等渠道正常使用。"], "urls": {"webpage": "https://finance.sina.com.cn/tech/roll/2023-06-29/doc-imyyxruu9872061.shtml", "image_url": []}}