{"title": "消息称传音 Infinix Note 30 系列手机 5 月底发布：支持 260W 有线 / 110W 无线快充传音无线快充IT之家", "news_website": "新浪科技", "author": "", "Managing Editor": "", "details": {"creation_time": "2023年05月11日 08:47", "keywords": ["传音", "无线快充", "IT之家", "电池"]}, "content": ["IT之家 5 月 11 日消息，据 GSMArena 报道，传音 Infinix 将在 5 月晚些时候发布新的 Note 30 系列手机，将配备该公司的 All-Round FastCharge 技术，支持高达 260W 有线充电和高达 110W 无线充电。", "预计传音 Infinix Note 30 中端手机采用最高快充，但也支持无线快充，价格低于 300 美元（IT之家备注：当前约 2079 元人民币）。", "预计传音将推出 Infinix Note 30 Pro、Note 30 VIP 和 Note 30 5G 等机型，还有内置 5000mAh 电池的 Note 30（4G）型号。"], "urls": {"webpage": "https://finance.sina.com.cn/tech/digi/2023-05-11/doc-imytkepf9630526.shtml", "image_url": []}}