{"title": "IDC：2022智能家居摄像头市场出货量超2000万台IDC智能家居出货量", "news_website": "新浪科技", "author": "", "Managing Editor": "", "details": {"creation_time": "2023年04月09日 13:58", "keywords": ["IDC", "智能家居", "出货量"]}, "content": ["2022年中国智能家居摄像头市场出货量超过2000万台，同比增长1.6%。", "近日消息，IDC公布了2022年中国智能家居摄像头市场情况。根据IDC《中国智能家居设备市场季度跟踪报告，2022年第四季度》显示，2022年中国智能家居摄像头市场出货量超过2000万台，同比增长1.6%。", "IDC表示过去一年中国智能家居摄像头市场在功能配置方面大幅升级，分辨率及夜视能力显著提升，但受整体消费环境影响，产品升级对市场需求的提振效果有限，市场出货量增速放缓。", "IDC预计，2023年中国智能家居摄像头市场出货量预计为2155万台，同比增长7.5%。伴随工作、生活节奏恢复常态，家庭安全监控智能化需求将逐步拓展，在传统安防需求升级的同时，老幼看护、宠物陪伴等泛安防场景需求将不断增长，进一步推动智能家居摄像头市场升级和发展。IDC表示2023年中国智能家居摄像头市场线下渠道仍有广阔的发展空间；AI能力将成为智能家居摄像头市场升级发展的重要方向之一；生态联动将融入更大市场。"], "urls": {"webpage": "https://finance.sina.com.cn/tech/mobile/n/n/2023-04-10/doc-imypumwf7877232.shtml", "image_url": ["https://n.sinaimg.cn/spider20230409/456/w720h536/20230409/aebf-558bff233feaad1911842a34905f27c2.png"]}}