{"title": "华纳《哈利波特：魁地奇冠军》实机视频泄露，10 个角色可选哈利波特：魁地奇冠军哈利波特", "news_website": "新浪科技", "author": "", "Managing Editor": "", "details": {"creation_time": "2023年05月22日 09:25", "keywords": ["哈利波特：魁地奇冠军", "哈利波特"]}, "content": ["IT之家 5 月 22 日消息，华纳兄弟游戏公司旗下以《哈利波特》为主题的独立多人游戏《哈利波特：魁地奇冠军》将登陆 PC 和主机平台，此前已经开启限量测试，网络上流传出一段游戏实机视频。", "游戏玩法与《哈利波特》电影中大致相同，金色飞贼（Golden Snitch）、游走球（Bludgers）、鬼飞球（Quaffle）等元素一应俱全；人物下方增加了“加速条”，停止加速后会回复。", "华纳兄弟游戏公司表示，《哈利波特：魁地奇冠军》是一款“以世界上最具标志性的魔法运动为特色的快节奏多人竞技游戏”，被称为“完整、独立的魁地奇体验”，让玩家在竞争激烈的多人游戏环境中与朋友一起参与魁地奇运动和其他飞天扫帚冒险。"], "urls": {"webpage": "https://finance.sina.com.cn/tech/digi/2023-05-22/doc-imyuriai3215097.shtml", "image_url": ["https://n.sinaimg.cn/spider20230522/338/w778h360/20230522/27c8-8a2ef2547d92e8937bf83a74d7c27707.jpg", "https://n.sinaimg.cn/spider20230522/3/w1026h577/20230522/5a25-79e510354c4f65b4a57eaa1988125433.png"]}}