{"title": "TCL宣布Mini LED电视Q10H发布，峰值亮度达3000nits", "news_website": "新浪财经", "author": "", "Managing Editor": "：刘万里 SF014", "details": {"creation_time": "2023年05月09日 19:32", "keywords": []}, "content": ["新浪科技讯 5月9日晚间消息，TCL今日宣布推出Mini LED电视Q10H，该电视峰值亮度可达3000nits，配备TCL华星高端A++蝶翼星曜屏，电视对比度提升了5倍，支持像素级控光。", "", "", "据介绍，此次发布的Q10H旗舰Mini LED电视共推出98英寸、85英寸、75英寸以及65英寸四款电视，日常价分别为29999元、17999元、13999元以及9999元，98英寸款首发售价直降4000元，其余几款分别降价3000-2000元。（文猛）"], "urls": {"webpage": "https://finance.sina.com.cn/tech/it/2023-05-09/doc-imytetuw0883728.shtml", "image_url": ["https://n.sinaimg.cn/finance/transform/59/w550h309/20230509/0568-5590b625957b84e4809d27c50fdd6da6.png"]}}