{"title": "30多年来首次 日本电子产品出现812亿日元逆差：手机、家电辉煌不再日本家电半导体", "news_website": "新浪科技", "author": "", "Managing Editor": "", "details": {"creation_time": "2023年02月19日 10:32", "keywords": ["日本", "家电", "半导体", "电子设备", "电子产品"]}, "content": ["据日本共同社消息，日本的电子设备产品30多年来首次出现逆差，相比巅峰期每年8万亿日元的顺差已经不再辉煌。", "据统计，2022年下半年（7至12月），日本电视机、手机等电子设备出口额减去进口额的贸易收支为812亿日元（约合人民币42亿元）逆差，这是自1988年以现行方式进行统计以来半年报出现逆差尚属首次。", "具体来看，        智能手机等“通信设备”为逆差17898亿日元，冰箱等“家用电器设备”为逆差4003亿日元，      电视机等“音响和影像设备（包括零件）”为逆差3093亿日元。", "不过日本在半导体方面依然有强大的实力， “半导体等电子零部件”为顺差3784亿日元，“电路等设备”也为顺差8136亿日元。"], "urls": {"webpage": "https://finance.sina.com.cn/tech/mobile/n/n/2023-02-20/doc-imyheyqx8712676.shtml", "image_url": []}}