{"title": "一亿像素主摄加持！8GB+256GB神机低至1269元realme", "news_website": "新浪财经", "author": "", "Managing Editor": "", "details": {"creation_time": "2023年03月29日 07:18", "keywords": ["realme", "5G"]}, "content": ["", "realme 真我 10 Pro 5G智能手机 8GB+256GB目前活动售价1299元，下单参与满100元减30元优惠活动，实付低至1269元，售价历史新低，综合性价比非常不错，有需要的小伙伴儿可以买起来了。", "realme 10 Pro是一款采用骁龙695八核处理器、6nm工艺、支持双卡5G的手机。其6.72英寸OLED材质直屏占比达到93.65%，支持最高120Hz刷新率、10.7亿色彩显示、100% P3广色域、1080*2400分辨率、5000000:1对比度、2160Hz高频调光和0.65mm二代钢化高强度保护玻璃。", "手机采用三星HM6传感器，f/1.75光圈，6P镜头，最高支持输出12000x9000分辨率。手机轻至173g，薄至8.1mm，内置5000mAh电池，搭配33W快充。", "此外，realme 10 Pro还拥有立体双扬声器，200%超大音量，IP54级防尘防水的特点。", "(8147407)"], "urls": {"webpage": "https://finance.sina.com.cn/tech/mobile/n/n/2023-03-29/doc-imynnsmq8361532.shtml", "image_url": ["https://n.sinaimg.cn/sinakd20230329s/345/w640h505/20230329/ff0d-a458afd066386daf0417de353f54da46.png"]}}