{"title": "英特尔单季营收跌32%：市值蒸发80亿美元 给不出年度业绩预期英特尔", "news_website": "新浪财经", "author": "", "Managing Editor": "：韦子蓉", "details": {"creation_time": "2023年01月28日 14:28", "keywords": ["英特尔"]}, "content": ["雷递网 乐天 1月28日", "英特尔日前公布了一份惨淡的财报。", "财报显示，英特尔2022年营收为631亿美元，较上年同期的790亿美元下跌20%；净利为80亿美元，较上年同期的净利199亿美元下跌60%。", "其中，英特尔2022年第四季度营收为140亿美元，较上年同期的205亿美元下跌32%；净亏损为6.61亿美元，上年同期的净利为46.23亿美元。", "具体来看，英特尔2022年第四季度来自Client Computing Group （客户运算事业群，CCG）营收为66亿美元，较上年同期下跌36%；全年营收为317亿美元，较上年同期下跌23%；", "英特尔2022年第四季度Data Center and AI （数据中心和人工智能事业群，DCAI）营收为43亿美元，较上年同期下降33%；全年营收为192亿美元，较上年同期下降15%；", "英特尔2022年第四季度Network and Edge （NEX）营收为21亿美元，较上年同期下降1%；全年营收为89亿美元，较上年同期增长11%。", "英特尔2022年第四季度来自Mobileye的营收为5.65亿美元，较上年同期增长59%；全年营收为19亿美元，较上年同期增长35%。", "英特尔在2022年支付60亿美元的股息。但随着现金流同比下降约140亿美元，第四季度业绩承压，一些华尔街人士质疑英特尔是否该削减股息了。", "但英特尔 （INTC） 首席执行官帕特·基辛格 （Pat Gelsinger） 驳斥了公司扭亏为盈将意味着其梦寐以求的股息支付结束的观点。", "基辛格表示：“我们致力于派发股息，并提供健康和有竞争力的股息。” “我们还在进行大型长期战略投资，因此我们将所有这些放在一起，非常仔细地研究公司整体的资本配置优先事项，即使我们仍然致力于以股息回报股东。”", "英特尔还以动荡的全球经济状况为由拒绝提供全年业绩指引。", "几天前，英特尔还宣布，董事长奥马尔·伊什拉克已辞职，并任命董事会董事弗兰克·耶里接替他的职位。", "奥马尔·伊什拉克是基辛格担任英特尔CEO的关键人物。", "基辛格表示：“奥马尔·伊什拉克在让我回到公司担任首席执行官方面发挥了重要作用，并在董事会和管理团队中培养了一种高影响力的工作氛围。”", "盖尔辛格于2021年从VMware回到英特尔担任首席执行官，推动英特尔的变革，英特尔正在重组业务以赶上竞争对手。", "此次财报发布后，英特尔股价大跌6.41%，市值蒸发80亿美元；截至目前，公司市值为1162亿美元。"], "urls": {"webpage": "https://finance.sina.com.cn/tech/it/2023-01-28/doc-imyctqsn0246946.shtml", "image_url": ["https://n.sinaimg.cn/finance/crawl/91/w550h341/20230128/006d-b6d369079180e7f6f9cc89adac955580.jpg", "https://n.sinaimg.cn/finance/crawl/769/w550h219/20230128/f111-7821e51f9221dd63713f3baad1d021ec.png", "https://n.sinaimg.cn/finance/crawl/779/w550h229/20230128/d96e-cc591d9ad59e5987d3d6159889c126f2.jpg", "https://n.sinaimg.cn/finance/crawl/729/w550h179/20230128/d847-db86ef5faf93dc086a8f75a4f0764848.jpg", "https://n.sinaimg.cn/finance/crawl/57/w550h307/20230128/8941-257ec499e991ae776881b56e265e90f8.jpg", "https://n.sinaimg.cn/finance/crawl/742/w550h192/20230128/a6eb-6afab3d20e4a0baee21437d628d248da.jpg"]}}