{"title": "与K60 Ultra同台发！Redmi 2K新平板曝光：只要千元华为平板redmi", "news_website": "新浪科技", "author": "", "Managing Editor": "：建嘉", "details": {"creation_time": "2023年06月14日 15:22", "keywords": ["华为平板", "redmi"]}, "content": ["快科技6月14日消息，按照之前多方爆料，Redmi K60 Ultra将于下月正式发布，换装天玑9200+，达到安卓性能天花板。", "最新爆料还透露，在该机的发布会上还有望推出一款全新平板产品，这也将是Redmi第二款平板。", "同时，相对较低的性能让功耗表现更好，平板的续航时间会明显增强，这对于入门定位的产品来说更重要。", "至于外观方面，大概率会维持之前的Redmi Pad设计，正面采用四边等宽的全面屏设计，后壳则为金属一体机身。", "【本文结束】如需转载请务必注明出处：快科技"], "urls": {"webpage": "https://finance.sina.com.cn/tech/mobile/n/n/2023-06-14/doc-imyxfxmc3645474.shtml", "image_url": ["https://n.sinaimg.cn/spider20230614/199/w600h399/20230614/e1ce-a12a1c16f82bda4d6dd79ce7eec9d024.jpg", "https://n.sinaimg.cn/spider20230614/777/w600h177/20230614/3b1e-14215dd40ed47f6b35030086ae301238.png"]}}