{"title": "华为 FreeBuds 5 至臻版无线耳机曝光：采用全曲面流线设计，超磁感澎湃单元华为耳机设计", "news_website": "新浪科技", "author": "", "Managing Editor": "", "details": {"creation_time": "2023年03月20日 07:34", "keywords": ["华为", "耳机", "设计", "降噪"]}, "content": ["IT之家 3 月 20 日消息，华为将于 3 月 23 日举行春季旗舰新品发布会，届时将亮相华为 FreeBuds 5 无线耳机。现在一款 FreeBuds 5 至臻版已经曝光。", "曝光的这款华为 FreeBuds 5 至臻版是演示样机，耳机型号为 T0013，充电盒型号为 T0013C，颜色为冰霜银。", "华为 FreeBuds 5 至臻版有几大特性，包括采用全面流线设计，超磁感澎湃单元，5C 超级快充（IT之家注：回盒充电 5 分钟，续航 2 小时），半入耳舒适降噪，AI 通话降噪，多设备连接等。", "华为预计将于 3 月 23 日发布会上公布华为P60系列、Mate X3 折叠屏、畅享 60 系列、FreeBuds 5 无线耳机、MatePad 11（2023 款）、全新商用品牌“华为擎云”等等。"], "urls": {"webpage": "https://finance.sina.com.cn/tech/mobile/n/n/2023-03-20/doc-imymnnse3351201.shtml", "image_url": ["https://n.sinaimg.cn/spider20230320/89/w690h999/20230320/6ba6-276f5cb2bd7e9a8f221982e7e664e8b4.jpg", "https://n.sinaimg.cn/spider20230320/345/w801h344/20230320/1896-c4aeff6d6b0fc059d40e87c4511df817.png", "https://n.sinaimg.cn/spider20230320/89/w690h999/20230320/2d27-f8b76f7321ae634fde6e226d029aa34a.jpg"]}}