{"title": "小米 13 Ultra 手机保外维修价格公布：屏幕更换需 1360 元小米徕卡", "news_website": "新浪科技", "author": "", "Managing Editor": "", "details": {"creation_time": "2023年04月23日 07:17", "keywords": ["小米", "徕卡"]}, "content": ["IT之家 4 月 23 日消息，小米 13 Ultra 是小米最新推出的旗舰机型，这款手机继续与徕卡联名，搭载了骁龙 8 Gen 2 移动平台和徕卡后置四摄模组，起售价 5999 元。目前，小米官方已经列出了小米 13 Ultra 备件保外维修价格，其中屏幕 1360 元，后置摄像头组件 1450 元。", "从官方列表中可以看到，小米 13 Ultra 的备件保外维修都包含 40 元的人工费。加上人工费后，屏幕更换价格达到了 1400 元、后置摄像头组件更换价格达到了 1490 元、主板更换价格达到了 2360 元、电池更换价格为 199 元、电池盖更换价格为 220。"], "urls": {"webpage": "https://finance.sina.com.cn/tech/mobile/n/n/2023-04-23/doc-imyrikkx5202419.shtml", "image_url": ["https://n.sinaimg.cn/spider20230423/599/w820h579/20230423/c994-40a4a3f797fabc98694b62e5ad969bab.jpg", "https://n.sinaimg.cn/spider20230423/481/w1304h777/20230423/c814-5e6ce8c1345a06fcf428a8a103477a12.png"]}}