{"title": "三星Galaxy A54保护套泄露 参数提前曝光只差价格保护套三星Galaxy三星", "news_website": "新浪科技", "author": "", "Managing Editor": "", "details": {"creation_time": "2023年03月06日 07:28", "keywords": ["保护套", "三星Galaxy", "三星", "设计"]}, "content": ["", "【手机中国新闻】近期，有关三星Galaxy A54的爆料消息不断从网上传出。目前来看，三星已准备好发布Galaxy A54智能手机了。在互联网上已经有很多关于Galaxy A54的泄露，包括手机参数配置和外观设计，这款新机实际上已经没有什么秘密可言。3月6日，手机中国注意到，三星在其马其顿官方门户网站上泄露了用于这款设备的智能视图钱包保护套。图片不仅展示其自身的外观设计，还展示了智能手机的外观。", "这款配件的官方名称是“Smart View Wallet Case”（智能视图钱包保护套），顾名思义，这是一个钱包式的保护套，内部有一个卡片空间和一个窗口来露出手机的部分显示屏，用于始终在线显示时钟等信息。", "虽然产品现在还不能正式购买，但三星已经发布了一组配件的渲染图。从渲染图来看，该配件本身看起来没有任何特别之处，但我们可以看到它所有颜色选项。在三星官网上，这个钱包保护套只有黑色一种颜色可供选择。但是图片信息显示，该产品还将提供石灰绿和薰衣草色。", "三星GalaxyA54保护套泄露", "另外官方泄露的图片中，三星Galaxy A54的外观设计与之前泄露的渲染图非常一致。可以看到，手机背面有三个独立的相机凸起，每个凸起都配备了一个摄像头。造型设计上，这款设备类似Galaxy S23。", "根据此前爆料消息，三星Galaxy A54采用6.4英寸AMOLED显示屏，分辨率为1080p，刷新率为120Hz；搭载Exynos 1380芯片，后置5000万像素主摄像头；内置5000毫安电池，支持25W充电。", ""], "urls": {"webpage": "https://finance.sina.com.cn/tech/mobile/n/n/2023-03-06/doc-imyiwsya3818848.shtml", "image_url": ["https://n.sinaimg.cn/spider20230306/169/w600h369/20230306/7fe1-8d7b79b0b176711b08a2f8534ebe0f91.png", "https://n.sinaimg.cn/spider20230306/128/w524h404/20230306/6c32-d8664f2ac750cc28339003d883e1bceb.jpg"]}}