{"title": "传承 Win7 设计，消息称微软 Win11 小部件可拆分固定在桌面微软it之家Windows", "news_website": "新浪科技", "author": "", "Managing Editor": "", "details": {"creation_time": "2023年05月06日 07:29", "keywords": ["微软", "it之家", "Windows", "Win11", "Win7"]}, "content": ["微软目前正进一步丰富小部件种类，已提供超过 13 种供用户试用。微软也一直在扩展小部件面板的功能，最近刚刚推出了新的全屏模式和小部件选择器，进一步完善了使用体验。", "报告称微软后续将会继续改进小部件，在丰富种类之外，允许用户自由的将某个小部件固定到桌面上，满足个性化使用需求。", "IT之家注：微软将于 Build 2023 开发者大会上，举办关于 Windows 小部件的专场活动，或许会公布更多相关的信息。"], "urls": {"webpage": "https://finance.sina.com.cn/tech/mobile/n/n/2023-05-06/doc-imysuuvz2653989.shtml", "image_url": ["https://n.sinaimg.cn/spider20230506/0/w1024h576/20230506/368f-9d506f63d6bd5308ae4088cec8686695.jpg", "https://n.sinaimg.cn/spider20230506/212/w580h432/20230506/185d-1296cd94f8d4b4a694a3275e6b15851c.jpg"]}}