{"title": "超级小桀电脑店翻车登顶贴吧热搜!众多粉丝怒删牌子", "news_website": "新浪科技", "author": "", "Managing Editor": "", "details": {"creation_time": "2023年08月18日 12:22", "keywords": []}, "content": ["昨日，知名主播超级小桀的装机店“小桀和他朋友们”在抖音商城开张，但店内部分电脑配置的价格及其硬件被质疑过高，引发了一场争议。 在开业前，超级小桀曾表示，他开设电脑店的目的是为了揭露和打击那些不良商家的欺诈行为。然而，他的店内售卖的一款售价约5万元的电脑，使用的是i3900K的CPU，但却配备了B760这样的中端主板。此外，网友计算出，这套配置的成本远低于5万元。同时，网友发现该配置中使用了口碑较差的金河田电源，许多玩家表示，电脑可以省其他部分，但绝不能省电源，因此，这样的配置并不是一个真正的“极客”会推荐的产品。 今日，超级小桀在直播间对此进行了回应，他表示，“一台机器的利润只有十几块钱”。这一话题在贴吧上引发了热议，成为了当日的热门话题。 以下是部分网友的评论："], "urls": {"webpage": "https://finance.sina.com.cn/tech/roll/2023-08-18/doc-imzhqvmf7455031.shtml", "image_url": []}}