{"title": "读速 7450 MB/s：梵想 2T 固态硬盘 499 元探底（长江存储晶圆）固态硬盘", "news_website": "新浪科技", "author": "", "Managing Editor": "", "details": {"creation_time": "2023年05月30日 14:29", "keywords": ["固态硬盘"]}, "content": ["梵想 2T 固态硬盘 S790 系列，读速 7450 MB/s，日常售价为 599 元。", "京东 618 大促期间，5 月 31 日 20 点~6 月 3 日，到手价为 499 元：", "另外，今日还可抽 3 次京东无门槛红包，支持即领即用，结算省上加省：点此抽取。", "梵想 S790 系列固态硬盘 2T 版，M.2 接口，PCIe 4.0 x4，读速 7450 MB/s，写速 6750 MB/s，长江储存晶圆，3D TLC 储存颗粒，联芸 1602 主控，石墨烯散热贴。", "具体参数如下：", ""], "urls": {"webpage": "https://finance.sina.com.cn/tech/mobile/n/n/2023-05-30/doc-imyvpune4307052.shtml", "image_url": ["https://n.sinaimg.cn/spider20230530/609/w1109h1100/20230530/fe64-d56e644f34a62f523130f9ecd8c1f9ff.png", "https://n.sinaimg.cn/spider20230530/429/w1106h923/20230530/5449-43394c8e763155246bfeeb0d4ef3ad07.png"]}}