{"title": "iPhone 15 Pro边框收窄 还有全新金色版配色iPhone苹果会设计", "news_website": "新浪科技", "author": "", "Managing Editor": "", "details": {"creation_time": "2023年02月16日 15:56", "keywords": ["iPhone", "苹果会", "设计"]}, "content": ["据爆料者透露，iPhone 15 Pro的边框将明显比以往更薄，尽管没有透露新的细节，但有较高的可信度。", "苹果iPhone 15和iPhone 15 Pro将会有多种差异化的设计，从而可以拉开它们之间的定位差距。据爆料者透露，iPhone 15 Pro的边框将明显比以往更薄，尽管没有透露新的细节，但有较高的可信度。", "iPhone 15 Pro预计将于2023年秋季推出，在Pro版机型中，苹果会采用钛合金机身，其能够带来更纤薄的机身，拥有更高强度的机身，也能把屏幕边框做薄。新机可能会具有略微弯曲的屏幕设计，类似的情况可以参考三星S23 Ultr，a总之，新机的边框要比iPhone 14 Pro更窄。", "泄密者此前曾透露，iPhone 15 Pro Max可能会采用亮度高达2500尼特的OLED显示屏，屏幕素质肯定是顶级的，与边框更窄、屏占比更大的全面屏结合，视觉感受肯定非常不错。", "另有消息人士透露，苹果会在iPhone 15 Pro系列中，提供一种全新的金色版本配色，它与苹果以往的金色配色会有些许区别，能够带来不同于以往的视觉效果。"], "urls": {"webpage": "https://finance.sina.com.cn/tech/roll/2023-02-17/doc-imyfwtzp2186493.shtml", "image_url": ["https://n.sinaimg.cn/spider20230216/325/w720h405/20230216/9a73-99762f4f4923ad8b080dc0caad71db8c.jpg", "https://n.sinaimg.cn/spider20230216/640/w720h720/20230216/299b-c1a2403779f1c16e923d3c9af326b1b6.jpg"]}}