{"title": "马斯克：今晚笼中决斗，我开特斯拉去小扎家，敢开门就直播", "news_website": "创事记", "author": "量子位", "Managing Editor": "", "details": {"creation_time": "2023-08-15 15:34:50", "keywords": []}, "content": ["丰色 萧箫 发自 凹非寺", "量子位 | 公众号 QbitAI", "“笼中格斗”这出戏，马斯克这回直接放了个大招：", "正好今晚要试驾特斯拉FSD，我让车直接开到小扎家。如果小扎真的开门，战斗就开始了！", "全程直播。", "亿万富翁，上门约架——这样的戏码让吃瓜观众的热情瞬间被点燃。", "眼看评论区的梗图又是“一路狂飙”，有AI马斯克按小扎门铃、甚至破窗而入的：", "△图源Teslaconomics&dustinthedad", "但小扎却顺势从后门逃跑了：", "个个全是看热闹不嫌事大。", "事情发展到这一步，或许还得从小扎前一天在Threads上的公开吐槽说起：", "从头到尾，马斯克都没认真对待过这场比赛，所以我也不奉陪了。", "没想到这“激将法”真有作用，马斯克直接将未定时间提前到了“今晚”。", "从赌城、意大利到小扎家门口", "吃瓜朋友们可能还记得，这场话题拉满的网络约架始于6月。", "最早是小扎的一句“地址发我”，马斯克将地点约在了终极格斗冠军赛（UFC）的比赛场地：拉斯维加斯八角笼。", "但其实一个多月过去，也没有给个具体日期。", "就在大伙儿都觉得这事没边之时，马斯克突然发推宣布要在𝕏平台直播这场战斗，并且将之作为一场慈善活动，把所有收益捐给退伍军人。", "与此同时，他还和意大利文化部长商定，更改原本的比赛地点，改在该国举行，活动主题也顺势定为古罗马风格。", "听着可算是“有鼻子有眼了”。", "小扎那边，则在戏谑了一把直播平台应该“选一个更可靠的”之后，提议了一个具体日期 （8月26日）以示应战。", "就在这之前，他已在自家后院安排了一个八角笼（为此还占用了老婆打理了两年的草坪），主打的就是一个认真备赛。", "然而，小扎等啊等，并没有等到马斯克跟他确定日子……", "但不管怎样，对格斗非常热爱的小扎并没有受太大影响，表示“时刻准备着”，并在不久之后发了一张一大早就在自家八角笼中练习的图片，看得出心情甚是美妙。", "反观马斯克，不仅没有确认小扎给的日期，还表示自己没时间训练，只能在办公室抽空练练举重。", "后面则又“借口”自己要做核磁共振检查可能要动手术，然后，然后直接短信问小扎能不能去他家后院训练……", "这把瞬间惹毛了小扎：", "如果你想真比赛，就自己练，练好了再来找我。", "接下来是重点，此时的小扎似乎终于明白老马一直都是在打嘴炮，他表示，再也不想一直炒作这件永远不会发生的事了。", "你自己决定到底要不要比，要比就麻溜的，不然我们就了结此事。", "这段对话由马斯克亲自爆料。", "可以说，整个过程，小扎都是非常认真对待邀约，但马斯克似乎有一搭没一搭的。", "而在小扎说完，马斯克这才回复他：好，那就这周一在他家的八角笼比（划重点：地点又被马斯克改了）。", "随后他还表示最近只和谁谁谁练了一场，并用当代李小龙打趣了小扎一番。", "对此，我们没有看到小扎做何回应，但就在昨天晚上，小扎在Threads上发了一大段信息回顾了马斯克从“慈善活动”到后院约训练这一系列操作，“明示”马斯克就是在炒作，他不玩了！", "我想我们都同意马斯克并不认真，是时候move on了。", "接下来我将专注于与认真对待这项运动的人比赛。", "对此，我们便看到了文章开头的那一幕：", "马斯克“急”了——今天直接宣布不请自来，亲自开车到小扎门口。", "当然，“顺便（主要目的）”测试一下自家特斯拉的FSD性能以及𝕏平台的直播功能。（手动狗头）", "一场APP之间的较量", "总结来看，两位亿万富翁的约架一路从赌城转至意大利再到小扎家门口，反应出来的两者态度，简直可以说是截然不同：", "小扎那叫一个认真，马斯克却从头到尾“变化无常”……", "现在来看，这把笼斗约战，实质上已变成了𝕏和Threads的流量争夺大戏。", "最初笼斗的导火索，就是Threads放出消息准备上线，马斯克被网友警告“扎克练过”时的一次嘴炮反击：", "7月6号Threads突击上线，扎克伯格在10年没发帖的推特上发了个梗图，嘲讽感拉满。", "Threads表现也不负众望，不到一周内注册新用户数量破亿，与Instagram关联的做法更是加速了这一进程，扎克伯格则不时在Threads上隔空喊话做出回应。", "与此同时，马斯克则在𝕏平台上展开攻击，反复提及笼斗的事情，甚至计划开𝕏直播进一步“引流”。", "那么，“笼斗导火索”Threads、和如今变身为“𝕏”的推特，流量收获如何？", "意外的是，一个月以来，Threads的流量相比最初已经下降了接近80%，至于使用时长，也从最高峰的每人每日19分钟，到如今只剩3分钟。", "据网络数据分析公司Similarweb和市场情报公司Sensor Tower统计变化情况：", "日活跃用户数量上，Threads的日活用户在7月7日达到峰值4390万，但到7月底日活实际用户数量降至1300万，下降70%；8月7日，这一数字已经回落到1030万，减少了79%。", "每日使用时长上，Threads的最初平均使用时长达到14分钟左右（峰值甚至达到过19分钟）；然而到7月底，这一时长已经下降至4分钟，到8月7日再跌至3分钟。", "据ZDNet分析，原因可能与Threads新功能上线太慢有关。目前，APP完整服务仅在手机上提供，“可编辑”功能一直没更新，同时网页版更是只能阅读不能发帖。", "相比之下，更名为𝕏的推特，日活用户似乎并未受到太大影响。", "光是安卓APP的日活跃用户就超过1亿，平均每人每天使用时长接近25分钟。", "△图源Similarweb", "至于这场笼斗的“带货”效果，对双方而言也是各有不同。", "虽然扎克伯格一直认真回应马斯克的笼斗，不过他在Threads上点赞量最高的一条帖子，还停留在1个月以前庆祝用户注册数破千万的时候：", "至于“笼斗”的关注量，则保持在几万点赞量：", "相比之下，前段时间马斯克仅仅是测试了一下用来直播“笼斗”的𝕏直播效果，就收获了50多万点赞，播放量达到上千万：", "流量这事儿，看来还是被马斯克玩明白了。", "但无论双方约战目的如何，大伙儿已经对这场笼斗逐渐冷静下来了。", "例如美国科技媒体Platformer就分析认为，尽管双方看起来战火“一触即发”，但小扎家门口这场笼斗，无论如何也不太可能发生。", "首先，扎克伯格现在根本不在家，而是在旅行；其次，有消息表示，马斯克的飞机早些时候降落在克利夫兰市，距离扎克伯格家（帕罗阿尔托）接近几千公里。", "The Verge则提到了马斯克之前毁约无数的“黑历史”：从他嘴里说出来的东西并没那么可信。", "不过，网友瓜倒是吃得很尽兴，毕竟光是两个亿万富翁线上吵架，话题性就拉满了。", "有网友做了个两人线上吵架凶猛，但一旦见面就不敢动手的梗图：", "还有不少网友注意力放在二者的战力值上。", "至于老马这回是嘴炮还是真的，嗯，今晚就见分晓了。"], "urls": {"webpage": "https://finance.sina.com.cn/tech/csj/2023-08-15/doc-imzhhkpz5169298.shtml", "image_url": ["https://n.sinaimg.cn/finance/crawl/82/w550h332/20230815/0d2f-ba2dcd40f4500ef7c3e00ff3b3ffe47f.png", "https://n.sinaimg.cn/finance/crawl/18/w550h268/20230815/77b1-6b13670e0df3d119ae5d728ff213a051.png", "https://n.sinaimg.cn/finance/crawl/369/w550h619/20230815/76c1-15af32729188a05291667c06817dc673.png", "https://n.sinaimg.cn/finance/crawl/348/w550h598/20230815/a38f-357361c02388f43deca9e4b8b63d584f.png", "https://n.sinaimg.cn/finance/crawl/26/w550h276/20230815/cd55-53180a5957034d5a0da7c764ed255a55.png", "https://n.sinaimg.cn/finance/crawl/287/w550h537/20230815/3f9d-3079ebdf103df6b3ff5596f9177767d6.png", "https://n.sinaimg.cn/finance/crawl/381/w550h631/20230815/533d-52702703de48e453d07f60c0b57b715d.png", "https://n.sinaimg.cn/finance/crawl/790/w550h240/20230815/6951-8e519894a943bf7d4203d6b7d97df048.png", "https://n.sinaimg.cn/finance/crawl/497/w550h747/20230815/2cd5-041ec4dc6419de2518c6c7eb39cc0bda.png", "https://n.sinaimg.cn/finance/crawl/189/w550h439/20230815/dff4-499f0f39336ffe34dd91a4e1987f81f6.png", "https://n.sinaimg.cn/finance/crawl/80/w550h330/20230815/9959-85c142d4c5d45239229d9a29b7ec45e1.png", "https://n.sinaimg.cn/finance/crawl/759/w550h209/20230815/2ceb-2385709bd672c834c44341f669ebe1b6.png", "https://n.sinaimg.cn/finance/crawl/156/w550h406/20230815/d03f-cf3f682ff5fdc371502236ac3ff31a0e.png", "https://n.sinaimg.cn/finance/crawl/340/w550h590/20230815/6208-d313b640277256c94ab174287882b87a.png", "https://n.sinaimg.cn/finance/crawl/127/w550h377/20230815/9304-970ea8c5d3355d9ee76f89ab42093e5c.png", "https://n.sinaimg.cn/finance/gif_image/221/w480h541/20230815/4aaa-gif8b4d74562523c0c53a19254f858a83ca.gif", "https:http://f.sinaimg.cn/finance/gif_image/110/w480h430/20230815/9c03-gif003c12cfb9b631e0e36fb054fb2a1400.gif", "https://n.sinaimg.cn/finance/crawl/322/w550h572/20230815/18be-b81584f95dfde601b4f61e257e7b8045.png", "https://n.sinaimg.cn/tech/47b4da8f/20210524/1.png"]}}