{"title": "软银与 Symbotic 成立合资公司，探索人工智能仓储解决方案软银集团人工智能仓储", "news_website": "新浪科技", "author": "", "Managing Editor": "", "details": {"creation_time": "2023年07月25日 13:26", "keywords": ["软银集团", "人工智能", "仓储", "it之家", "人民币"]}, "content": ["据悉，总部位于美国马萨诸塞州威尔明顿的 Symbotic 公司，主要提供机器人仓库自动化解决方案，沃尔玛是该公司的主要支持者和客户。目前 Symbotic 公司正在帮助沃尔玛改造旗下商业仓库，以实现基于 AI 的自动化仓储管理。", "此次交易将使软银获得 Symbotic 公司约 2% 的流通股票的认股权证，软银还从 Symbotic 首席执行官 Rick Cohen 手中购买了 1780 万股 Symbotic 公司股票，令软银集团在 Symbotic 公司中的持股比例从此前的约 5% 增至当下的 8%。", "Symbotic 公司表示，一旦合资企业开始运营，预计将获得来自软件、零部件和服务销售的每年超过 5 亿美元的持续收入。截至 2022 财年，Symbotic 报告的收入为 5.933 亿美元（约 42.43 亿元人民币），同比增长 136%，亏损 1.391 亿美元（约 9.95 亿元人民币）。", "广告声明：文内含有的对外跳转链接（包括不限于超链接、二维码、口令等形式），用于传递更多信息，节省甄选时间，结果仅供参考，IT之家所有文章均包含本声明。"], "urls": {"webpage": "https://finance.sina.com.cn/tech/digi/2023-07-25/doc-imzcwnsx4431004.shtml", "image_url": []}}